{
  "source": "reports/track_b_b4/logs/events_66cc066ac32549ebad6f882f9241d54c.jsonl",
  "n_snapshots": 6,
  "snapshots": [
    {
      "ts": 1779555255.9553652,
      "event": "buffer_position_class_snapshot",
      "step": 500,
      "n_sampled": 5000,
      "buffer_size": 27743,
      "colony_n": 469,
      "extension_n": 595,
      "neither_n": 3936,
      "colony_frac": 0.0938,
      "extension_frac": 0.119,
      "neither_frac": 0.7872,
      "colony_mean_value_target": 0.0512,
      "extension_mean_value_target": 0.0605,
      "neither_mean_value_target": 0.0201
    },
    {
      "ts": 1779556043.0555208,
      "event": "buffer_position_class_snapshot",
      "step": 1000,
      "n_sampled": 5000,
      "buffer_size": 53833,
      "colony_n": 453,
      "extension_n": 572,
      "neither_n": 3975,
      "colony_frac": 0.0906,
      "extension_frac": 0.1144,
      "neither_frac": 0.795,
      "colony_mean_value_target": 0.0177,
      "extension_mean_value_target": -0.049,
      "neither_mean_value_target": 0.0438
    },
    {
      "ts": 1779556831.397199,
      "event": "buffer_position_class_snapshot",
      "step": 1500,
      "n_sampled": 5000,
      "buffer_size": 79256,
      "colony_n": 462,
      "extension_n": 578,
      "neither_n": 3960,
      "colony_frac": 0.0924,
      "extension_frac": 0.1156,
      "neither_frac": 0.792,
      "colony_mean_value_target": -0.0022,
      "extension_mean_value_target": -0.1176,
      "neither_mean_value_target": 0.0283
    },
    {
      "ts": 1779557633.3207514,
      "event": "buffer_position_class_snapshot",
      "step": 2000,
      "n_sampled": 5000,
      "buffer_size": 105364,
      "colony_n": 450,
      "extension_n": 624,
      "neither_n": 3926,
      "colony_frac": 0.09,
      "extension_frac": 0.1248,
      "neither_frac": 0.7852,
      "colony_mean_value_target": 0.0556,
      "extension_mean_value_target": -0.0753,
      "neither_mean_value_target": 0.0458
    },
    {
      "ts": 1779558477.1084216,
      "event": "buffer_position_class_snapshot",
      "step": 2500,
      "n_sampled": 5000,
      "buffer_size": 133860,
      "colony_n": 456,
      "extension_n": 569,
      "neither_n": 3975,
      "colony_frac": 0.0912,
      "extension_frac": 0.1138,
      "neither_frac": 0.795,
      "colony_mean_value_target": 0.0395,
      "extension_mean_value_target": -0.0035,
      "neither_mean_value_target": 0.0211
    },
    {
      "ts": 1779559266.7838848,
      "event": "buffer_position_class_snapshot",
      "step": 3000,
      "n_sampled": 5000,
      "buffer_size": 160327,
      "colony_n": 492,
      "extension_n": 558,
      "neither_n": 3950,
      "colony_frac": 0.0984,
      "extension_frac": 0.1116,
      "neither_frac": 0.79,
      "colony_mean_value_target": 0.0081,
      "extension_mean_value_target": -0.0269,
      "neither_mean_value_target": 0.0248
    }
  ]
}